Metadata-Version: 2.4
Name: docstring_parser_fork
Version: 0.0.14
Summary: Parse Python docstrings in reST, Google and Numpydoc format
Project-URL: homepage, https://github.com/rr-/docstring_parser
Project-URL: repository, https://github.com/rr-/docstring_parser
Project-URL: changelog, https://github.com/rr-/docstring_parser/blob/master/CHANGELOG.md
Author-email: Marcin Kurczewski <dash@wind.garden>
License: MIT
License-File: LICENSE.md
Classifier: Development Status :: 4 - Beta
Classifier: Environment :: Other Environment
Classifier: Intended Audience :: Developers
Classifier: License :: OSI Approved :: MIT License
Classifier: Natural Language :: English
Classifier: Operating System :: OS Independent
Classifier: Programming Language :: Python :: 3.8
Classifier: Programming Language :: Python :: 3.9
Classifier: Programming Language :: Python :: 3.10
Classifier: Programming Language :: Python :: 3.11
Classifier: Programming Language :: Python :: 3.12
Classifier: Programming Language :: Python :: 3.13
Classifier: Topic :: Documentation :: Sphinx
Classifier: Topic :: Software Development :: Libraries :: Python Modules
Classifier: Topic :: Text Processing :: Markup
Requires-Python: >=3.8
Provides-Extra: dev
Requires-Dist: docstring-parser[docs]; extra == 'dev'
Requires-Dist: docstring-parser[test]; extra == 'dev'
Requires-Dist: pre-commit>=2.16.0; (python_version >= '3.9') and extra == 'dev'
Provides-Extra: docs
Requires-Dist: pydoctor>=25.4.0; extra == 'docs'
Provides-Extra: test
Requires-Dist: pytest; extra == 'test'
